odoo/addons/sale_order_type_confirm_message/README.rst
odoo/addons/sale_order_type_confirm_message/__init__.py
odoo/addons/sale_order_type_confirm_message/__manifest__.py
odoo/addons/sale_order_type_confirm_message/i18n/es.po
odoo/addons/sale_order_type_confirm_message/i18n/it.po
odoo/addons/sale_order_type_confirm_message/i18n/sale_order_type_confirm_message.pot
odoo/addons/sale_order_type_confirm_message/models/__init__.py
odoo/addons/sale_order_type_confirm_message/models/sale_order.py
odoo/addons/sale_order_type_confirm_message/models/sale_order_type.py
odoo/addons/sale_order_type_confirm_message/readme/CONFIGURE.md
odoo/addons/sale_order_type_confirm_message/readme/CONTRIBUTORS.md
odoo/addons/sale_order_type_confirm_message/readme/DESCRIPTION.md
odoo/addons/sale_order_type_confirm_message/readme/USAGE.md
odoo/addons/sale_order_type_confirm_message/security/ir.model.access.csv
odoo/addons/sale_order_type_confirm_message/static/description/icon.png
odoo/addons/sale_order_type_confirm_message/static/description/icon.svg
odoo/addons/sale_order_type_confirm_message/static/description/index.html
odoo/addons/sale_order_type_confirm_message/tests/__init__.py
odoo/addons/sale_order_type_confirm_message/tests/test_sale_order_type_confirm_message.py
odoo/addons/sale_order_type_confirm_message/views/sale_order_type_view.xml
odoo/addons/sale_order_type_confirm_message/wizards/__init__.py
odoo/addons/sale_order_type_confirm_message/wizards/sale_order_type_confirm_message_wizard.py
odoo/addons/sale_order_type_confirm_message/wizards/sale_order_type_confirm_message_wizard_view.xml
odoo_addon_sale_order_type_confirm_message-17.0.1.0.0.6.dist-info/METADATA
odoo_addon_sale_order_type_confirm_message-17.0.1.0.0.6.dist-info/WHEEL
odoo_addon_sale_order_type_confirm_message-17.0.1.0.0.6.dist-info/top_level.txt
odoo_addon_sale_order_type_confirm_message-17.0.1.0.0.6.dist-info/RECORD
