Metadata-Version: 2.1
Name: odoo-addon-sale_order_type_confirm_message
Version: 17.0.1.0.0.6
Requires-Python: >=3.10
Requires-Dist: odoo-addon-sale_order_type>=17.0dev,<17.1dev
Requires-Dist: odoo>=17.0a,<17.1dev
Summary: Confirmation requirement when validating sale
Home-page: https://github.com/OCA/sale-workflow
License: AGPL-3
Author: Sygel, Odoo Community Association (OCA)
Author-email: support@odoo-community.org
Classifier: Programming Language :: Python
Classifier: Framework :: Odoo
Classifier: Framework :: Odoo :: 17.0
Classifier: License :: OSI Approved :: GNU Affero General Public License v3
